{"7Lrfe0gW5Ps": 0, "-D88g6EUfC0": 0, "oInhe_1bsUs": 0, "OrYZEepTQ5M": 0, "cxxAiczjM00": 0, "D8Rd0xh1El8": 0, "7Ohd26TbJA0": 0, "TSqaKMm1IAs": 0, "ktpLFz8FR_Q": 0, "0Nr4b1iCFyc": 0, "DzP6B99A3g4": 0, "ZvEj4zB_uh4": 0, "VPMHyWQ7nTE": 0, "cbdNZyq6TMk": 0, "W1buYqUbtmY": 0, "CTz4EYM1Obs": 0, "ngpncYHp_xU": 0, "PH2qODQTFOs": 0, "DtZFfbEKkLY": 0, "BZzc5NmMvrI": 0, "ensUi8Te544": 0, "3ZHKItpI1ZU": 0, "QjrCw6SbPgM": 0, "FSocpT0ttvQ": 0, "UtQ5ZL3-0zQ": 0, "WKS0OdRvO68": 0, "EyZOLUlSX9U": 0, "DC1KbTFyBas": 0, "JaLt21R-QF4": 0, "Az9YgDSgIWI": 0, "ELtfNUsKT78": 0, "DaYpYk0kVpQ": 0, "YUHK3CTybo4": 0, "LiUY4TQ0CmE": 0, "uI4jm7uFvVk": 0, "Qkfk7SP2x7E": 0, "6qVU2eWvmg8": 0, "HF6O9VYnjCs": 0, "VcbqHM7sKts": 0, "56Lgk1G9z4I": 0, "vvCsk8SPVG8": 0, "zogl1xmqAUc": 0, "3UFUfv9n420": 0, "5OpYudBVa1s": 0, "C68jhiJ6Ijg": 0, "WGXEs-zHJ4M": 0, "cX329JK3iz8": 0, "hGbEKNV6UxU": 0, "9dz0c0UsmnQ": 0, "_s7O0OWohvE": 0, "aAoFUt-RW-c": 0, "IFKGdJiF_2s": 0, "dU6LwptKvYg": 0, "xELjqNZjmaM": 0, "HpJX_0XqO4g": 0, "__kdsgQteFI": 0, "IL4RO7huoNw": 0, "r-DTKzMqUxA": 0, "4DBfnl-Jbag": 0, "9hf39EplVjI": 0, "B9rVsDd6PcQ": 0, "ETKejRszZpQ": 0, "EZa_gclmrl8": 0, "rbZ8879k7Hc": 0, "IfhNVRgq1to": 0, "IIyhXzWOuw4": 0, "ElwPvpm0lVE": 0, "bxy_2jLBwzA": 0, "zO7A9pHSfmI": 0, "qySVffwCNYY": 0, "o3O6v79neWM": 0, "K2vxGq9GSTE": 0, "F-gYNKjLZzo": 0, "N4MGm-gYcvY": 0, "2kM2mEVxJSo": 0, "9T0_gpCObos": 0, "hyl82xZkZsY": 0, "C1cNYRhYkqo": 0, "Z1fL3szztvk": 0, "RTMIAJ2k8qg": 0, "NpOGJ8oUezY": 0, "3DSfTGHX4fM": 0, "tL3LIZlEZic": 0, "lqHb69aPbCI": 0, "8SFCY0vS0EE": 0, "lC85KcDFY2Q": 0, "BJnb3mnImQ8": 0, "4RpjTcahXUk": 0, "CP6up7US6fA": 0, "QyiXRG3UDS0": 0, "ESA0OXek-Bs": 0, "iBRH9Po3gw8": 0, "Q7w5IMyJ3pM": 0, "iLcsiYu35E4": 0, "W8hT-mbEBn4": 0, "T781JHL4NVE": 0, "31enbGkAKaU": 0, "25rf_ZORC6g": 0, "hiTZ_adGxrM": 0, "XLls1jWT2AQ": 0, "b3Re0HnxU00": 0, "g56gvsJx7Nw": 0, "VN8wVyc8Uf8": 0, "M4EPHOfgOdc": 0, "V7_O6_LffBw": 0, "L6yAQI_Zhyk": 0, "suCmElos4Q8": 0, "U7qOSjrR8Bg": 0, "NFvoXfxX0bg": 0, "KtsvxCnJBLs": 0, "rIWYrjXs4b4": 0, "v_4EZUMzw4s": 0, "yOfpwM51d9M": 0, "4WMMVpzlHss": 0, "CBWr85G0l7k": 0, "ae41AFdIcRI": 0, "k9N6qD-c4a4": 0}